dethklok-1.0.0.dist-info/dependency_links.txt
dethklok-1.0.0.dist-info/entry_points.txt
dethklok-1.0.0.dist-info/METADATA
dethklok-1.0.0.dist-info/top_level.txt
dethklok-1.0.0.dist-info/WHEEL
dethklok/_cli.py
dethklok/__init__.py
dethklok/__main__.py
dethklok-1.0.0.dist-info/LICENSE
dethklok-1.0.0.dist-info/RECORD