Metadata-Version: 2.1
Name: dethklok
Version: 1.0.0
Summary: The most uncompromising Python code formatter ever!
Project-URL: Repository, https://github.com/orsinium-labs/dethklok
Author: Gram
Author-email: mail@orsinium.dev
License: MIT
Requires-Python: >=3.6
Keywords: formatter,black,autopep8
Classifier: Development Status :: 4 - Beta
Classifier: Environment :: Console
Classifier: Intended Audience :: Developers
Classifier: License :: OSI Approved :: MIT License
Classifier: Programming Language :: Python
Classifier: Topic :: Software Development
Requires-Dist: astunparse
Requires-Dist: autopep8
